kwess/__init__.py
kwess-0.0.7.dist-info/LICENSE.txt
kwess-0.0.7.dist-info/METADATA
kwess-0.0.7.dist-info/WHEEL
kwess-0.0.7.dist-info/top_level.txt
kwess-0.0.7.dist-info/zip-safe
kwess-0.0.7.dist-info/RECORD
