Metadata-Version: 2.1
Name: kwess
Version: 0.0.7
Summary: Questrade API wrapper.
Home-page: https://github.com/kaiyoux/kwess
Author: Issa Lompo
Author-email: kaiyoux@gmail.com
Maintainer: Issa Lompo
Maintainer-email: kaiyoux@gmail.com
License: GNU General Public License v3 (GPLv3)
Project-URL: Bug Tracker, https://github.com/kaiyoux/kwess/issues
Keywords: Questrade,api,REST,wrapper
Classifier: Programming Language :: Python :: 3
Classifier: License :: OSI Approved :: GNU General Public License v3 (GPLv3)
Classifier: Operating System :: OS Independent
Classifier: Development Status :: 5 - Production/Stable
Classifier: Intended Audience :: Developers
Requires-Python: >=3.6
License-File: LICENSE.txt
Requires-Dist: requests >=2.28.1
